synpla_imagethumb-0.1.0.dist-info/RECORD
synpla_imagethumb-0.1.0.dist-info/DESCRIPTION.rst
synpla_imagethumb-0.1.0.dist-info/top_level.txt
synpla_imagethumb-0.1.0.dist-info/METADATA
synpla_imagethumb-0.1.0.dist-info/WHEEL
synpla_imagethumb-0.1.0.dist-info/metadata.json
synpla_imagethumb/__init__.py
synpla_imagethumb/templates/imagethumb/macros/imagethumb.html
